nuon/__init__.py
nuon/api_client.py
nuon/api_response.py
nuon/configuration.py
nuon/exceptions.py
nuon/py.typed
nuon/rest.py
nuon/api/__init__.py
nuon/api/apps_api.py
nuon/api/components_api.py
nuon/api/general_api.py
nuon/api/installers_api.py
nuon/api/installs_api.py
nuon/api/orgs_api.py
nuon/api/releases_api.py
nuon/api/runner_runners_api.py
nuon/api/runners_api.py
nuon/api/runners_runner_api.py
nuon/api/sandboxes_api.py
nuon/api/vcs_api.py
nuon/models/__init__.py
nuon/models/app_account.py
nuon/models/app_account_type.py
nuon/models/app_app.py
nuon/models/app_app_aws_delegation_config.py
nuon/models/app_app_config.py
nuon/models/app_app_config_fmt.py
nuon/models/app_app_config_status.py
nuon/models/app_app_input.py
nuon/models/app_app_input_config.py
nuon/models/app_app_input_group.py
nuon/models/app_app_installer.py
nuon/models/app_app_installer_metadata.py
nuon/models/app_app_runner_config.py
nuon/models/app_app_runner_type.py
nuon/models/app_app_sandbox_config.py
nuon/models/app_app_sandbox_config_artifacts.py
nuon/models/app_app_secret.py
nuon/models/app_aws_account.py
nuon/models/app_awsecr_image_config.py
nuon/models/app_azure_account.py
nuon/models/app_cloud_platform.py
nuon/models/app_cloud_platform_region.py
nuon/models/app_component.py
nuon/models/app_component_build.py
nuon/models/app_component_config_connection.py
nuon/models/app_component_release.py
nuon/models/app_component_release_step.py
nuon/models/app_component_type.py
nuon/models/app_connected_github_vcs_config.py
nuon/models/app_docker_build_component_config.py
nuon/models/app_external_image_component_config.py
nuon/models/app_helm_component_config.py
nuon/models/app_install.py
nuon/models/app_install_component.py
nuon/models/app_install_deploy.py
nuon/models/app_install_deploy_type.py
nuon/models/app_install_event.py
nuon/models/app_install_inputs.py
nuon/models/app_install_sandbox_run.py
nuon/models/app_installer.py
nuon/models/app_installer_metadata.py
nuon/models/app_installer_type.py
nuon-0.19.216.dist-info/LICENSE
nuon-0.19.216.dist-info/METADATA
nuon-0.19.216.dist-info/WHEEL
nuon-0.19.216.dist-info/top_level.txt
nuon-0.19.216.dist-info/RECORD
