Metadata-Version: 2.1
Name: nuon
Version: 0.19.216
Summary: Nuon
Home-page: 
Author: Nuon Support
Author-email: support@nuon.co
Keywords: OpenAPI,OpenAPI-Generator,Nuon
License-File: LICENSE
Requires-Dist: urllib3 <2.1.0,>=1.25.3
Requires-Dist: python-dateutil
Requires-Dist: pydantic >=2
Requires-Dist: typing-extensions >=4.7.1
